{
  "case_id": "case_0100",
  "source": {
    "path": "",
    "novel_name": "045.天王",
    "author": "",
    "genre": "玄幻奇幻",
    "sub_genre": ""
  },
  "scene": {
    "type": "开篇",
    "position": "chapter_1",
    "word_count": 1000
  },
  "content": "第一章【落难王子殿】\n　　早晨九点。\n　　叮咚～店门被推开，门铃响起。\n　　“欢迎光临～”\n　　彬彬有礼的问候，在柜台后穿着快餐店制服的陈潇赶紧鞠躬，对着进来的人露出职业的微笑。他的脸庞白皙，五官俊秀，只是脸色之中却带着一丝淡淡的苍白，显得人略微文弱了一些。\n　　可进来这人摘下了帽子，却露出一张俏脸，粉颊含笑，双颊上更是各有一个浅浅的梨窝。这女孩子的面容来说也只是清秀而已，算不得什么大美女，偏偏是这笑容和可爱的小酒窝，给她平添了几分可人。\n　　陈潇看清来人，这才站直了身体，叹了口气：“你又迟到了，不怕经理扣你薪水么？”\n　　这女孩子吐了吐舌头，扮了个可爱鬼脸：“不怕！我知道你一定会帮我找借口啦……”口中虽然说不怕，可是却下意识的小心翼翼往店里后面看了两眼。\n　　“经理不在——嗯，还有，他刚才问起你的时候，我告诉她你去送外卖。”陈潇看了一下挂在墙上的时钟，然后从口袋里掏出一张外卖订单：“诺，一会儿把这个东西给经理看，可别出卖我啊。”\n　　“谢啦，改天介绍美女给你认识哦。”女孩子嘻嘻一笑接过，跑到后面的“员工室”里去换了工作服出来，和陈潇一起站在了柜台后。她扎了一个清爽的马尾辫，一张没有被",
  "techniques": [],
  "quality_score": 10,
  "has_ai_taste": false,
  "extract_time": "2026-03-31T21:18:50.289319"
}